<?xml version="1.0" encoding="UTF-8"?>
<record_update table="x_184790_vrealize_vrealize_instance_details">
    <x_184790_vrealize_vrealize_instance_details action="INSERT_OR_UPDATE">
        <active>true</active>
        <description/>
        <end_point>https://vra-01a.corp.local/</end_point>
        <entitlement_script/>
        <header_icon/>
        <homepage_image/>
        <homepage_renderer display_value="Category Items">47ebe8aa3742300054b6a3549dbe5dfa</homepage_renderer>
        <icon/>
        <image/>
        <location/>
        <mid_server display_value="MID_SERVER_1">3b6dd627db2b0300c6d773278c961948</mid_server>
        <mobile_hide_description>false</mobile_hide_description>
        <mobile_picture/>
        <mobile_subcategory_render_type>list</mobile_subcategory_render_type>
        <module/>
        <order>0</order>
        <parent/>
        <roles/>
        <sc_catalog/>
        <show_in_cms>false</show_in_cms>
        <sys_class_name>x_184790_vrealize_vrealize_instance_details</sys_class_name>
        <sys_created_by>admin</sys_created_by>
        <sys_created_on>2018-02-06 09:36:11</sys_created_on>
        <sys_id>0e46276adb801300c6d773278c96197d</sys_id>
        <sys_mod_count>18</sys_mod_count>
        <sys_name>3b6dd627db2b0300c6d773278c961948</sys_name>
        <sys_package display_value="vrealize-automation-servicenow-plugin-3-0" source="x_184790_vrealize">7345ec9adb7f0300c6d773278c961918</sys_package>
        <sys_policy/>
        <sys_scope display_value="vrealize-automation-servicenow-plugin-3-0">7345ec9adb7f0300c6d773278c961918</sys_scope>
        <sys_update_name>x_184790_vrealize_vrealize_instance_details_0e46276adb801300c6d773278c96197d</sys_update_name>
        <sys_updated_by>admin</sys_updated_by>
        <sys_updated_on>2018-02-06 10:56:19</sys_updated_on>
        <title>vrealize test 34</title>
        <token/>
        <vrealize_name>vrealize test 34</vrealize_name>
    </x_184790_vrealize_vrealize_instance_details>
    <sys_translated_text action="delete_multiple" query="documentkey=0e46276adb801300c6d773278c96197d"/>
</record_update>
